bargtd/__init__.py
bargtd-0.0.1a1.data/scripts/bargtd
bargtd-0.0.1a1.dist-info/LICENSE
bargtd-0.0.1a1.dist-info/METADATA
bargtd-0.0.1a1.dist-info/WHEEL
bargtd-0.0.1a1.dist-info/top_level.txt
bargtd-0.0.1a1.dist-info/RECORD
