Metadata-Version: 2.1
Name: bargtd
Version: 0.0.1a1
Summary: A GTD tool in the titlebar
Home-page: https://github.com/lidaobing/bargtd
Author: LI Daobing
Author-email: lidaobing@gmail.com
License: UNKNOWN
Platform: UNKNOWN
Classifier: Programming Language :: Python :: 3
Classifier: License :: OSI Approved :: MIT License
Classifier: Operating System :: OS Independent
